lems/__init__.py
lems/data_formater.py
lems/loss.py
lems/metrics.py
lems/models.py
lems-0.1.1.dist-info/METADATA
lems-0.1.1.dist-info/WHEEL
lems-0.1.1.dist-info/RECORD
